[
    {
        "id": 1,
        "name": "إذاعة القرآن\nمن البحرين",
        "uniqueName": "bahrain",
        "url": "https://5c7b683162943.streamlock.net:443/live/ngrp:radio-106-1_all/playlist.m3u8",
        "image": "https://s3.eu-west-2.amazonaws.com/qmasters/flags/png/bahrain/flag-round-250.png",
        "description": "106.1FM",
        "category": "editorsChoice",
        "isFavorite": true,
        "sharingDescription": "إذاعة القرآن الكريم من البحرين"
    },
    {
        "id": 2,
        "name": "إذاعة القرآن\nمن السعودية",
        "uniqueName": "saudi",
        "url": "https://win.holol.com/live/quran/playlist.m3u8",
        "image": "https://i.pinimg.com/564x/3a/a1/a1/3aa1a107c9434ca52b42b2dd0ffc896f.jpg",
        "description": "96.8FM",
        "category": "editorsChoice",
        "isFavorite": false,
        "sharingDescription": "إذاعة القرآن الكريم من السعودية"
    },
    {
        "id": 3,
        "name": "إذاعة القرآن\nمن الشارقة",
        "uniqueName": "sahreqa",
        "url": "https://svs.itworkscdn.net/smcquranlive/quranradiolive/playlist.m3u8",
        "image": "https://blogger.googleusercontent.com/img/b/R29vZ2xl/AVvXsEj8XMtpbvPbq9cS9F2kaLp5oOYJWeckbBgTXD7PIgEEzwr1fmpvfLD2FgP9T_oWXzhYwvlTRbFW43-K6lOW88bEJ4EMEDLanLi4bREv9sKQHpnmQ79hOxRtPCKsc3s8SYHuDsGIZMDIHX0/s1600/539798_ico.png",
        "description": "102.7FM",
        "category": "editorsChoice",
        "isFavorite": false,
        "sharingDescription": "إذاعة القرآن الكريم من الشارقة"
    },
    {
        "id": 4,
        "name": "السنة النبوية\nمن المدينة",
        "uniqueName": "madeena",
        "url": "https://win.holol.com/live/sunnah/playlist.m3u8",
        "image": "https://upload.wikimedia.org/wikipedia/ar/e/e9/%D8%B4%D8%B9%D8%A7%D8%B1_%D9%82%D9%86%D8%A7%D8%A9_%D8%A7%D9%84%D8%B3%D9%86%D8%A9_%D8%A7%D9%84%D9%86%D8%A8%D9%88%D9%8A%D8%A9.png",
        "description": "100FM",
        "category": "editorsChoice",
        "isFavorite": false,
        "sharingDescription": "إذاعة السنة النبوية من المدينة المنورة"
    },
    {
        "id": 5,
        "name": "القرآن الكريم\nالمنشاوي مجود",
        "uniqueName": "menshaweMegawad",
        "url": "https://backup.qurango.net/radio/mohammed_siddiq_alminshawi_mojawwad",
        "image": "https://png.pngtree.com/png-vector/20210326/ourlarge/pngtree-quran-book-cover-arabic-calligraphy-with-floral-border-png-image_3117635.jpg",
        "description": "LIVE",
        "category": "quran",
        "isFavorite": false,
        "sharingDescription": "القرآن الكريم للشيخ محمد صديق المنشاوي مجود"
    },
    {
        "id": 6,
        "name": "القرآن الكريم\nمحمد أيوب",
        "uniqueName": "quyoob",
        "url": "https://backup.qurango.net/radio/mohammed_ayyub",
        "image": "https://png.pngtree.com/png-vector/20210326/ourlarge/pngtree-quran-book-cover-arabic-calligraphy-with-floral-border-png-image_3117635.jpg",
        "description": "LIVE",
        "category": "quran",
        "isFavorite": false,
        "sharingDescription": "القرآن الكريم للشيخ محمد أيوب"
    },
    {
        "id": 7,
        "name": "القرآن الكريم\nعلي جابر",
        "uniqueName": "ghaper",
        "url": "https://backup.qurango.net/radio/ali_jaber",
        "image": "https://png.pngtree.com/png-vector/20210326/ourlarge/pngtree-quran-book-cover-arabic-calligraphy-with-floral-border-png-image_3117635.jpg",
        "description": "LIVE",
        "category": "quran",
        "isFavorite": false,
        "sharingDescription": "القرآن الكريم للشيخ علي جابر"
    },
    {
        "id": 8,
        "name": "القرآن الكريم\nعبدالباسط",
        "uniqueName": "abdulbasit",
        "url": "https://backup.qurango.net/radio/abdulbasit_abdulsamad_mojawwad",
        "image": "https://png.pngtree.com/png-vector/20210326/ourlarge/pngtree-quran-book-cover-arabic-calligraphy-with-floral-border-png-image_3117635.jpg",
        "description": "LIVE",
        "category": "quran",
        "isFavorite": false,
        "sharingDescription": "القرآن الكريم للشيخ عبدالباسط عبدالصمد"
    },
    {
        "id": 9,
        "name": "القرآن الكريم\nعلي الحذيفي",
        "uniqueName": "hozaifwei",
        "url": "https://backup.qurango.net/radio/ali_alhuthaifi_qalon",
        "image": "https://png.pngtree.com/png-vector/20210326/ourlarge/pngtree-quran-book-cover-arabic-calligraphy-with-floral-border-png-image_3117635.jpg",
        "description": "LIVE",
        "category": "quran",
        "isFavorite": false,
        "sharingDescription": "القرآن الكريم للشيخ علي الحذيفي"
    },
    {
        "id": 10,
        "name": "القرآن الكريم\nالمنشاوي مرتل",
        "uniqueName": "menshaweTarteel",
        "url": "https://backup.qurango.net/radio/mohammed_siddiq_alminshawi",
        "image": "https://png.pngtree.com/png-vector/20210326/ourlarge/pngtree-quran-book-cover-arabic-calligraphy-with-floral-border-png-image_3117635.jpg",
        "description": "LIVE",
        "category": "quran",
        "isFavorite": true,
        "sharingDescription": "القرآن الكريم للشيخ محمد صديق المنشاوي مرتل"
    },
    {
        "id": 11,
        "name": "القرآن الكريم\nالبنا مرتل",
        "uniqueName": "banaaTarteel",
        "url": "https://backup.qurango.net/radio/mahmoud_ali__albanna",
        "image": "https://png.pngtree.com/png-vector/20210326/ourlarge/pngtree-quran-book-cover-arabic-calligraphy-with-floral-border-png-image_3117635.jpg",
        "description": "LIVE",
        "category": "quran",
        "isFavorite": false,
        "sharingDescription": "القرآن الكريم للشيخ محمود علي البنا مرتل"
    },
    {
        "id": 12,
        "name": "القرآن الكريم\nالبنا مجود",
        "uniqueName": "banaaMegawad",
        "url": "https://backup.qurango.net/radio/mahmoud_ali__albanna_mojawwad",
        "image": "https://png.pngtree.com/png-vector/20210326/ourlarge/pngtree-quran-book-cover-arabic-calligraphy-with-floral-border-png-image_3117635.jpg",
        "description": "LIVE",
        "category": "quran",
        "isFavorite": false,
        "sharingDescription": "القرآن الكريم للشيخ محمود علي البنا مجود"
    },
    {
        "id": 13,
        "name": "القرآن الكريم\nمحمد الطبلاوي",
        "uniqueName": "tablawe",
        "url": "https://backup.qurango.net/radio/mohammad_altablaway",
        "image": "https://png.pngtree.com/png-vector/20210326/ourlarge/pngtree-quran-book-cover-arabic-calligraphy-with-floral-border-png-image_3117635.jpg",
        "description": "LIVE",
        "category": "quran",
        "isFavorite": false,
        "sharingDescription": "القرآن الكريم للشيخ محمد الطبلاوي"
    },
    {
        "id": 14,
        "name": "القرآن الكريم\nإدريس أبكر",
        "uniqueName": "edries",
        "url": "https://backup.qurango.net/radio/idrees_abkr",
        "image": "https://png.pngtree.com/png-vector/20210326/ourlarge/pngtree-quran-book-cover-arabic-calligraphy-with-floral-border-png-image_3117635.jpg",
        "description": "LIVE",
        "category": "quran",
        "isFavorite": false,
        "sharingDescription": "القرآن الكريم للشيخ إدريس أبكر"
    },
    {
        "id": 15,
        "name": "المختصر في \nتفسير القرآن",
        "uniqueName": "tafseerMoktaser",
        "url": "https://backup.qurango.net/radio/mukhtasartafsir",
        "image": "https://t3.ftcdn.net/jpg/02/69/64/56/360_F_269645677_oAjFKkNrezyIeJ6TmawcwEmERIXlQgi5.jpg",
        "description": "LIVE",
        "category": "more",
        "isFavorite": false,
        "sharingDescription": "المختصر في تفسير القرآن الكريم"
    },
    {
        "id": 16,
        "name": "تفسير الطبري \nفي القرآن",
        "uniqueName": "tafseerTabre",
        "url": "https://backup.qurango.net/radio/tabri",
        "image": "https://t3.ftcdn.net/jpg/02/69/64/56/360_F_269645677_oAjFKkNrezyIeJ6TmawcwEmERIXlQgi5.jpg",
        "description": "LIVE",
        "category": "more",
        "isFavorite": true,
        "sharingDescription": "تفسير الطبري من كتابه جامع البيان عن تأويل آي القرآن"
    },
    {
        "id": 17,
        "name": "تكبيرات العيد",
        "uniqueName": "eid",
        "url": "https://backup.qurango.net/radio/eid",
        "image": "https://t3.ftcdn.net/jpg/02/69/64/56/360_F_269645677_oAjFKkNrezyIeJ6TmawcwEmERIXlQgi5.jpg",
        "description": "LIVE",
        "category": "more",
        "isFavorite": false,
        "sharingDescription": "تكبيرات العيد"
    },
    {
        "id": 18,
        "name": "الرقية الشرعية",
        "uniqueName": "roqya",
        "url": "https://backup.qurango.net/radio/roqiah",
        "image": "https://t3.ftcdn.net/jpg/02/69/64/56/360_F_269645677_oAjFKkNrezyIeJ6TmawcwEmERIXlQgi5.jpg",
        "description": "LIVE",
        "category": "more",
        "isFavorite": false,
        "sharingDescription": "الرقية الشرعية"
    },
    {
        "id": 19,
        "name": "أذكار الصباح",
        "uniqueName": "azkarMorning",
        "url": "https://backup.qurango.net/radio/athkar_sabah",
        "image": "https://t3.ftcdn.net/jpg/02/69/64/56/360_F_269645677_oAjFKkNrezyIeJ6TmawcwEmERIXlQgi5.jpg",
        "description": "LIVE",
        "category": "more",
        "isFavorite": false,
        "sharingDescription": "أذكار الصباح"
    },
    {
        "id": 20,
        "name": "أذكار المساء",
        "uniqueName": "azkarNight",
        "url": "https://backup.qurango.net/radio/athkar_masa",
        "image": "https://t3.ftcdn.net/jpg/02/69/64/56/360_F_269645677_oAjFKkNrezyIeJ6TmawcwEmERIXlQgi5.jpg",
        "description": "LIVE",
        "category": "more",
        "isFavorite": true,
        "sharingDescription": "أذكار المساء"
    }
]